dagster_gitlab/__init__.py
dagster_gitlab/clients.py
dagster_gitlab/py.typed
dagster_gitlab/resources.py
dagster_gitlab/sensors.py
dagster_gitlab/_utils/__init__.py
dagster_gitlab/_utils/type_guards.py
dagster_gitlab/_utils/warn.py
dagster_gitlab-0.0.4.dist-info/METADATA
dagster_gitlab-0.0.4.dist-info/WHEEL
dagster_gitlab-0.0.4.dist-info/licenses/LICENSE
dagster_gitlab-0.0.4.dist-info/RECORD
